earthnet_models_pytorch/__init__.py
earthnet_models_pytorch/data/__init__.py
earthnet_models_pytorch/data/en21_data.py
earthnet_models_pytorch/data/en21x_data.py
earthnet_models_pytorch/data/en21x_data_old.py
earthnet_models_pytorch/data/en22_data.py
earthnet_models_pytorch/data/en23_data.py
earthnet_models_pytorch/metric/__init__.py
earthnet_models_pytorch/metric/earthnetscore.py
earthnet_models_pytorch/metric/nnse.py
earthnet_models_pytorch/metric/rmse.py
earthnet_models_pytorch/model/__init__.py
earthnet_models_pytorch/model/channel_u_net.py
earthnet_models_pytorch/model/conditioning_layer.py
earthnet_models_pytorch/model/contextformer.py
earthnet_models_pytorch/model/convlstm_ae.py
earthnet_models_pytorch/model/enc_dec_layer.py
earthnet_models_pytorch/model/layer_utils.py
earthnet_models_pytorch/model/local_rnn.py
earthnet_models_pytorch/model/nextframe_resnet.py
earthnet_models_pytorch/model/nextframe_unet.py
earthnet_models_pytorch/model/predrnn.py
earthnet_models_pytorch/model/rnn.py
earthnet_models_pytorch/model/simvp.py
earthnet_models_pytorch/model/spatiotemporal_unet.py
earthnet_models_pytorch/model/unet_lstm.py
earthnet_models_pytorch/task/__init__.py
earthnet_models_pytorch/task/loss.py
earthnet_models_pytorch/task/shedule.py
earthnet_models_pytorch/task/workflow.py
earthnet_models_pytorch/utils/__init__.py
earthnet_models_pytorch/utils/logging.py
earthnet_models_pytorch/utils/parse.py
earthnet_models_pytorch-0.1.1.data/scripts/debug.py
earthnet_models_pytorch-0.1.1.data/scripts/slurmrun.sh
earthnet_models_pytorch-0.1.1.data/scripts/test.py
earthnet_models_pytorch-0.1.1.data/scripts/train.py
earthnet_models_pytorch-0.1.1.data/scripts/tune.py
earthnet_models_pytorch-0.1.1.dist-info/licenses/LICENSE
earthnet_models_pytorch-0.1.1.dist-info/METADATA
earthnet_models_pytorch-0.1.1.dist-info/WHEEL
earthnet_models_pytorch-0.1.1.dist-info/top_level.txt
earthnet_models_pytorch-0.1.1.dist-info/RECORD
