Metadata-Version: 2.4
Name: earthnet-models-pytorch
Version: 0.1.1
Summary: EarthNet Models PyTorch
Home-page: https://earthnet.tech
Author: Vitus Benson, Claire Robin
Author-email: {vbenson, crobin}@bgc-jena.mpg.de
Classifier: Intended Audience :: Science/Research
Classifier: License :: Other/Proprietary License
Classifier: Programming Language :: Python :: 3
License-File: LICENSE
Requires-Dist: tensorboard
Requires-Dist: numpy
Requires-Dist: matplotlib
Requires-Dist: pillow
Requires-Dist: xarray
Requires-Dist: zarr
Requires-Dist: netcdf4
Requires-Dist: pytorch-lightning
Requires-Dist: earthnet
Requires-Dist: segmentation-models-pytorch
Dynamic: author
Dynamic: author-email
Dynamic: classifier
Dynamic: description
Dynamic: description-content-type
Dynamic: home-page
Dynamic: license-file
Dynamic: requires-dist
Dynamic: summary
